linesdk/__init__.py
linesdk/_nbdev.py
linesdk/linesdk.py
linesdk/schema.py
linesdk/slack.py
pynamoLogger/__init__.py
pynamoLogger/_nbdev.py
pynamoLogger/logger.py
pynamoLogger-0.0.2.dist-info/LICENSE
pynamoLogger-0.0.2.dist-info/METADATA
pynamoLogger-0.0.2.dist-info/WHEEL
pynamoLogger-0.0.2.dist-info/entry_points.txt
pynamoLogger-0.0.2.dist-info/top_level.txt
pynamoLogger-0.0.2.dist-info/RECORD
